prg/__init__.py
prg/prg.py
pyprg-0.1.1b7.dist-info/DESCRIPTION.rst
pyprg-0.1.1b7.dist-info/METADATA
pyprg-0.1.1b7.dist-info/RECORD
pyprg-0.1.1b7.dist-info/WHEEL
pyprg-0.1.1b7.dist-info/metadata.json
pyprg-0.1.1b7.dist-info/top_level.txt
