Metadata-Version: 1.1
Name: pyprg
Version: 0.1.1b7
Summary: Creates the Precision-Recall-Gain curve and calculates the area under the curve
Home-page: https://github.com/meeliskull/prg
Author: Meelis Kull, Peter Flach, Telmo de Menezes e Silva Filho, Miquel Perello Nieto
Author-email: meelis.kull@gmail.com
License: MIT + file LICENSE
Keywords: classifier evaluation precision recall gain
Platform: UNKNOWN
Classifier: Development Status :: 4 - Beta
Classifier: Environment :: Console
Classifier: Intended Audience :: Science/Research
Classifier: License :: OSI Approved :: MIT License
Classifier: Operating System :: OS Independent
Classifier: Programming Language :: Python :: 2
Classifier: Programming Language :: Python :: 3
Classifier: Topic :: Scientific/Engineering
